fast_fmm_rpy2/__init__.py
fast_fmm_rpy2/fmm_run.py
fast_fmm_rpy2/ingest.py
fast_fmm_rpy2/plot_fui.py
fast_fmm_rpy2-1.0.3.dist-info/METADATA
fast_fmm_rpy2-1.0.3.dist-info/WHEEL
fast_fmm_rpy2-1.0.3.dist-info/licenses/LICENSE
fast_fmm_rpy2-1.0.3.dist-info/RECORD
