Metadata-Version: 2.4
Name: fast-fmm-rpy2
Version: 1.0.3
Summary: FLMM rpy2 wrapper for analyzing Fiber Photometry data
Project-URL: Homepage, https://github.com/nimh-dsst/fast-fmm-rpy2
Project-URL: Issues, https://github.com/nimh-dsst/fast-fmm-rpy2/issues
Author-email: Josh Lawrimore <josh.lawrimore@gmail.com>, Ashley Ptinis <aptinis@gmail.com>, Gabriel Loewinger <gloewinger@gmail.com>
License: CC0 1.0 Universal
License-File: LICENSE
Keywords: FLMM,Fast Functional Mixed Models,Fast Univariate Inference,Fiber Photometry,Functional Linear Mixed Models
Requires-Python: >=3.10
Requires-Dist: matplotlib
Requires-Dist: pandas
Requires-Dist: rpy2>=3.6
Provides-Extra: dev
Requires-Dist: bump-my-version>=1.2.0; extra == 'dev'
Requires-Dist: mypy; extra == 'dev'
Requires-Dist: pandas-stubs; extra == 'dev'
Requires-Dist: pytest; extra == 'dev'
Requires-Dist: ruff; extra == 'dev'
